web3_proxy_providers/__init__.py
web3_proxy_providers/_sample_subscription.py
web3_proxy_providers/providers/__init__.py
web3_proxy_providers/providers/async_http.py
web3_proxy_providers/providers/async_websocket.py
web3_proxy_providers/providers/async_websocket_subscription.py
web3_proxy_providers/providers/http.py
web3_proxy_providers/providers/websocket.py
web3_proxy_providers/utils/__init__.py
web3_proxy_providers/utils/encoding.py
web3_proxy_providers/utils/proxy.py
web3_proxy_providers-0.3.dist-info/LICENSE
web3_proxy_providers-0.3.dist-info/METADATA
web3_proxy_providers-0.3.dist-info/WHEEL
web3_proxy_providers-0.3.dist-info/top_level.txt
web3_proxy_providers-0.3.dist-info/RECORD
