Metadata-Version: 2.1
Name: web3-proxy-providers
Version: 0.3
Summary: Proxy providers for web3py (Web3 python)
Home-page: https://github.com/sinarezaei/web3_proxy_providers
Author: Sina Rezaei
Author-email: sinarezaei1991@gmail.com
License: MIT
Classifier: Programming Language :: Python :: 3
Classifier: License :: OSI Approved :: MIT License
Classifier: Operating System :: OS Independent
Requires-Python: >=3.6
License-File: LICENSE
Requires-Dist: web3 (>=6.0.0b9)
Requires-Dist: websockets (==10.4)
Requires-Dist: aiohttp (>=3.8.3)
Requires-Dist: aiohttp-socks (>=0.7.1)
Requires-Dist: PySocks (>=1.7.1)
